sample_project/__init__.py
sample_project/main.py
soos_sample_project-1.0.2.dist-info/LICENSE
soos_sample_project-1.0.2.dist-info/METADATA
soos_sample_project-1.0.2.dist-info/WHEEL
soos_sample_project-1.0.2.dist-info/entry_points.txt
soos_sample_project-1.0.2.dist-info/top_level.txt
soos_sample_project-1.0.2.dist-info/RECORD
