Metadata-Version: 2.1
Name: soos-sample-project
Version: 1.0.2
Summary: SOOS ( https://soos.io ) is an independent software security company, located in Winooski, VT USA, building security software for your team. Used for testing purposes, this package is an example of a vulnerable package on a public registry.
Home-page: https://github.com/soos-io/sample-project-python
Author: SOOS
Author-email: dev@soos.io
License: UNKNOWN
Project-URL: Issues, https://github.com/soos-io/sample-project-python/issues
Project-URL: Source, https://github.com/soos-io/sample-project-python
Project-URL: About, https://soos.io
Project-URL: Register, https://app.soos.io/register
Keywords: soos,sca,package,sample,project,example,vulnerabilities,licenses,sbom,governance,dast,open source,oss
Platform: UNKNOWN
Classifier: Development Status :: 3 - Alpha
Classifier: License :: OSI Approved :: MIT License
Classifier: Intended Audience :: Developers
Classifier: Programming Language :: Python :: 3
Requires-Python: <4,>=3.6
License-File: LICENSE
Requires-Dist: requests (==2.26.0)
Requires-Dist: certifi (==2020.6.20)
Requires-Dist: idna (==2.10)
Requires-Dist: urllib3 (==1.26.5)
Requires-Dist: charset-normalizer (==2.0.12)
